billions/__init__.py
billions/admin.py
billions/apps.py
billions/fields.py
billions/models.py
billions/tests.py
billions/utils.py
billions/views.py
billions/widgets.py
billions/migrations/__init__.py
billions-1.0.dist-info/LICENSE
billions-1.0.dist-info/METADATA
billions-1.0.dist-info/WHEEL
billions-1.0.dist-info/top_level.txt
billions-1.0.dist-info/RECORD
