Metadata-Version: 2.1
Name: billions
Version: 1.0
Summary: 基于Django的Markdown组件
Home-page: https://github.com/wupeiqi/billions
Author: wupeiqi
Author-email: wupeiqi@live.com
License: UNKNOWN
Platform: UNKNOWN
Classifier: Programming Language :: Python :: 3
Classifier: License :: OSI Approved :: MIT License
Classifier: Operating System :: OS Independent
Requires-Python: >=3
Requires-Dist: pillow
